jsmol_bokeh_extension/__init__.py
jsmol_bokeh_extension/jsmol.py
jsmol_bokeh_extension/jsmol.ts
jsmol_bokeh_extension-0.2.0.dist-info/METADATA
jsmol_bokeh_extension-0.2.0.dist-info/WHEEL
jsmol_bokeh_extension-0.2.0.dist-info/top_level.txt
jsmol_bokeh_extension-0.2.0.dist-info/RECORD
