Metadata-Version: 2.1
Name: jsmol-bokeh-extension
Version: 0.2.0
Summary: bokeh extension for jsmol
Home-page: https://github.com/ltalirz/jsmol-bokeh-extension
Author: Leopold Talirz
Author-email: leopold.talirz@gmail.com
License: Creative Commons
Platform: UNKNOWN
Classifier: Programming Language :: Python
Requires-Dist: bokeh (>=1.1)
Provides-Extra: pre-commit
Requires-Dist: pre-commit (==1.11.0) ; extra == 'pre-commit'
Requires-Dist: yapf (==0.24.0) ; extra == 'pre-commit'
Requires-Dist: prospector (==1.1.5) ; extra == 'pre-commit'
Requires-Dist: pylint (==1.9.3) ; extra == 'pre-commit'
